autocast/__init__.py
autocast/autocast.py
python_autocast-1.dist-info/DESCRIPTION.rst
python_autocast-1.dist-info/METADATA
python_autocast-1.dist-info/RECORD
python_autocast-1.dist-info/WHEEL
python_autocast-1.dist-info/metadata.json
python_autocast-1.dist-info/top_level.txt
